Metadata-Version: 2.1
Name: blake-test-54681681
Version: 2.8.5
Summary: Thoughtful is a python package by Thoughtful for helping manage automations with helpful packages like supervisor
Home-page: https://thoughtful.ai
License: Apache-2.0
Keywords: rpa,robot-framework,robocorp,automation
Author: Thoughtful Automation
Author-email: care@thoughtful.ai
Requires-Python: >=3.8,<3.12
Classifier: Framework :: Robot Framework
Classifier: Framework :: Robot Framework :: Library
Classifier: Framework :: Robot Framework :: Tool
Classifier: License :: OSI Approved :: Apache Software License
Classifier: Programming Language :: Python :: 3
Classifier: Programming Language :: Python :: 3.8
Classifier: Programming Language :: Python :: 3.9
Classifier: Programming Language :: Python :: 3.10
Classifier: Programming Language :: Python :: 3.11
Classifier: Topic :: Security :: Cryptography
Provides-Extra: screen-recorder
Requires-Dist: aws-requests-auth (>=0.4.3,<0.5.0)
Requires-Dist: boto3 (>=1.24.64,<2.0.0)
Requires-Dist: chevron (>=0.14.0,<0.15.0)
Requires-Dist: imageio (>=2.34.2,<3.0.0) ; extra == "screen-recorder"
Requires-Dist: imageio-ffmpeg (>=0.5.1,<0.6.0) ; extra == "screen-recorder"
Requires-Dist: isodate (>=0.6.1,<0.7.0)
Requires-Dist: moto (>=4.0.5,<5.0.0)
Requires-Dist: numpy (>=1.24.4,<2.0.0) ; extra == "screen-recorder"
Requires-Dist: pillow (>=10.4.0,<11.0.0) ; extra == "screen-recorder"
Requires-Dist: pre-commit (>=2.17.0,<3.0.0)
Requires-Dist: pyconfs (>=0.5.5,<0.6.0)
Requires-Dist: pydantic (>=2.5.2,<3.0.0)
Requires-Dist: pyjwt (>=2.8.5,<3.0.0)
Requires-Dist: pyyaml (>=5.4.1)
Requires-Dist: requests (>=2.28.1,<3.0.0)
Requires-Dist: robotframework-seleniumlibrary (>=6.5.0,<7.0.0) ; extra == "screen-recorder"
Project-URL: Documentation, https://thoughtful-supervisor.readthedocs-hosted.com/en/latest/index.html
Project-URL: Repository, https://github.com/thoughtful-automation/thoughtful
